{
  "lastUpdated": "2025-07-07T00:00:34.878Z",
  "stats": {
    "users": {
      "count": 27931,
      "change": -4
    },
    "revenue": {
      "amount": 185236,
      "change": 3.8
    },
    "projects": {
      "count": 362,
      "change": 3.6
    },
    "tasks": {
      "count": 2030,
      "change": 19.9
    }
  },
  "activities": [
    {
      "type": "payment",
      "title": "Task assigned",
      "timestamp": "2025-07-07T00:00:34.878Z"
    },
    {
      "type": "message",
      "title": "User updated profile",
      "timestamp": "2025-07-06T00:00:13.395Z"
    },
    {
      "type": "task",
      "title": "System alert",
      "timestamp": "2025-07-05T00:00:09.642Z"
    },
    {
      "type": "user",
      "title": "New message",
      "timestamp": "2025-07-04T00:00:44.839Z"
    },
    {
      "type": "alert",
      "title": "System alert",
      "timestamp": "2025-07-03T00:01:02.146Z"
    }
  ],
  "weeklyActivity": [
    {
      "day": "Mon",
      "value": 17
    },
    {
      "day": "Tue",
      "value": 83
    },
    {
      "day": "Wed",
      "value": 35
    },
    {
      "day": "Thu",
      "value": 61
    },
    {
      "day": "Fri",
      "value": 54
    },
    {
      "day": "Sat",
      "value": 13
    },
    {
      "day": "Sun",
      "value": 72
    }
  ],
  "performanceMetrics": [
    {
      "date": "2023-09-26",
      "value": 31
    },
    {
      "date": "2023-09-27",
      "value": 44
    },
    {
      "date": "2023-09-28",
      "value": 41
    },
    {
      "date": "2023-09-29",
      "value": 26
    },
    {
      "date": "2023-09-30",
      "value": 19
    },
    {
      "date": "2023-10-01",
      "value": 27
    },
    {
      "date": "2023-10-02",
      "value": 45
    }
  ]
}