{
  "lastUpdated": "2025-05-24T00:00:31.853Z",
  "stats": {
    "users": {
      "count": 9225,
      "change": 8.8
    },
    "revenue": {
      "amount": 91872,
      "change": 4.4
    },
    "projects": {
      "count": 344,
      "change": 4.1
    },
    "tasks": {
      "count": 1316,
      "change": 11.2
    }
  },
  "activities": [
    {
      "type": "payment",
      "title": "New user registered",
      "timestamp": "2025-05-24T00:00:31.853Z"
    },
    {
      "type": "payment",
      "title": "System alert",
      "timestamp": "2025-05-23T17:49:33.568Z"
    },
    {
      "type": "user",
      "title": "New user registered",
      "timestamp": "2023-08-15T10:24:32Z"
    },
    {
      "type": "project",
      "title": "Project 'Marketing Campaign' created",
      "timestamp": "2023-08-15T09:15:22Z"
    },
    {
      "type": "task",
      "title": "Task 'Update documentation' completed",
      "timestamp": "2023-08-15T08:45:11Z"
    }
  ],
  "weeklyActivity": [
    {
      "day": "Mon",
      "value": 55
    },
    {
      "day": "Tue",
      "value": 94
    },
    {
      "day": "Wed",
      "value": 37
    },
    {
      "day": "Thu",
      "value": 72
    },
    {
      "day": "Fri",
      "value": 50
    },
    {
      "day": "Sat",
      "value": 86
    },
    {
      "day": "Sun",
      "value": 32
    }
  ],
  "performanceMetrics": [
    {
      "date": "2023-08-11",
      "value": 25
    },
    {
      "date": "2023-08-12",
      "value": 30
    },
    {
      "date": "2023-08-13",
      "value": 20
    },
    {
      "date": "2023-08-14",
      "value": 15
    },
    {
      "date": "2023-08-15",
      "value": 10
    },
    {
      "date": "2023-08-16",
      "value": 34
    },
    {
      "date": "2023-08-17",
      "value": 27
    }
  ]
}