{
  "lastUpdated": "2025-07-04T00:00:44.839Z",
  "stats": {
    "users": {
      "count": 25751,
      "change": 13.8
    },
    "revenue": {
      "amount": 181140,
      "change": 9.9
    },
    "projects": {
      "count": 360,
      "change": -3.9
    },
    "tasks": {
      "count": 1987,
      "change": -3.2
    }
  },
  "activities": [
    {
      "type": "user",
      "title": "New message",
      "timestamp": "2025-07-04T00:00:44.839Z"
    },
    {
      "type": "alert",
      "title": "System alert",
      "timestamp": "2025-07-03T00:01:02.146Z"
    },
    {
      "type": "payment",
      "title": "New user registered",
      "timestamp": "2025-07-02T00:01:01.638Z"
    },
    {
      "type": "message",
      "title": "New user registered",
      "timestamp": "2025-07-01T00:00:17.158Z"
    },
    {
      "type": "alert",
      "title": "Task completed",
      "timestamp": "2025-06-30T00:00:11.607Z"
    }
  ],
  "weeklyActivity": [
    {
      "day": "Mon",
      "value": 10
    },
    {
      "day": "Tue",
      "value": 88
    },
    {
      "day": "Wed",
      "value": 52
    },
    {
      "day": "Thu",
      "value": 70
    },
    {
      "day": "Fri",
      "value": 35
    },
    {
      "day": "Sat",
      "value": 10
    },
    {
      "day": "Sun",
      "value": 52
    }
  ],
  "performanceMetrics": [
    {
      "date": "2023-09-23",
      "value": 34
    },
    {
      "date": "2023-09-24",
      "value": 11
    },
    {
      "date": "2023-09-25",
      "value": 26
    },
    {
      "date": "2023-09-26",
      "value": 31
    },
    {
      "date": "2023-09-27",
      "value": 44
    },
    {
      "date": "2023-09-28",
      "value": 41
    },
    {
      "date": "2023-09-29",
      "value": 26
    }
  ]
}